{
  "template": "default",
  "locales": {
    "en": {
      "headline": "stay focused,\nget more done",
      "screenshot": "assets/placeholder.svg",
      "backgroundColor": "#6C5CE7",
      "textColor": "#FFFFFF"
    },
    "ja": {
      "headline": "集中を保ち、\nもっと成果を出そう",
      "screenshot": "assets/placeholder.svg",
      "backgroundColor": "#6C5CE7",
      "textColor": "#FFFFFF"
    },
    "zh": {
      "headline": "保持专注，\n高效完成更多",
      "screenshot": "assets/placeholder.svg",
      "backgroundColor": "#6C5CE7",
      "textColor": "#FFFFFF"
    },
    "ko": {
      "headline": "집중을 유지하고\n더 많은 성과를",
      "screenshot": "assets/placeholder.svg",
      "backgroundColor": "#6C5CE7",
      "textColor": "#FFFFFF"
    }
  }
}
